sphinx_diagram_connect/__init__.py
sphinx_diagram_connect-1.0.0.dist-info/LICENSE
sphinx_diagram_connect-1.0.0.dist-info/METADATA
sphinx_diagram_connect-1.0.0.dist-info/WHEEL
sphinx_diagram_connect-1.0.0.dist-info/RECORD
