Metadata-Version: 2.3
Name: sphinx-diagram-connect
Version: 1.0.0
Summary: sphinx-diagram-connect is a Sphinx extension to resolve std:ref-s defined in plantuml files
License: MIT License
Author: Michael Parkes
Author-email: mparkes@post.cz
Requires-Python: >=3.10,<4.0
Classifier: License :: Other/Proprietary License
Classifier: Programming Language :: Python :: 3
Classifier: Programming Language :: Python :: 3.10
Classifier: Programming Language :: Python :: 3.11
Classifier: Programming Language :: Python :: 3.12
Classifier: Programming Language :: Python :: 3.13
Requires-Dist: lxml (>=5.4.0,<6.0.0)
Requires-Dist: sphinx (>=6.1.3)
Requires-Dist: sphinx-needs (>=2.0.0)
